BitMask/__init__.py
BitMask/bitmask_module.py
bitmaskfunctionalities-1.2.2.dist-info/METADATA
bitmaskfunctionalities-1.2.2.dist-info/WHEEL
bitmaskfunctionalities-1.2.2.dist-info/licenses/LICENSE.txt
bitmaskfunctionalities-1.2.2.dist-info/RECORD
