Metadata-Version: 2.4
Name: BitMaskFunctionalities
Version: 1.2.2
Summary: A package for creating and manipulating BitMasks
Project-URL: Repository, https://github.com/AThieringer/BitMask
Project-URL: Download, https://github.com/AThieringer/BitMask/releases
Project-URL: Changelog, https://github.com/AThieringer/BitMask/blob/master/Changelog
Author-email: Adam Thieringer <adamt0408@gmail.com>
License-Expression: MIT
License-File: LICENSE.txt
Keywords: BitMask,binary,bit,bitset,data,flags
Classifier: Development Status :: 5 - Production/Stable
Requires-Python: >=3.11
